<?xml version="1.0" encoding="UTF-8"?><export xmlns:xsi="http://www.w3.org/2001/XMLSchema-instance" xmlns="http://zakupki.gov.ru/oos/export/1" xmlns:oos="http://zakupki.gov.ru/oos/types/1">
  <tenderPlan schemeVersion="1.0">
    <oos:commonInfo>
      <oos:id>446284</oos:id>
      <oos:planNumber>44201403763000194</oos:planNumber>
      <oos:year>2014</oos:year>
      <oos:versionNumber>2</oos:versionNumber>
      <oos:owner>
        <oos:regNum>03763000194</oos:regNum>
        <oos:fullName>Муниципальное бюджетное учреждение &quot;Межпоселенческий Центр народной культуры Майкопского района&quot;</oos:fullName>
      </oos:owner>
      <oos:createDate>2014-02-13T14:42:48Z</oos:createDate>
      <oos:description>План-график муниципального бюджетного учреждения &quot;Межпоселенческий Центр народной культуры Майкопского района&quot;</oos:description>
      <oos:confirmDate>2014-01-14T00:00:00Z</oos:confirmDate>
      <oos:publishDate>2014-02-13T15:55:05Z</oos:publishDate>
    </oos:commonInfo>
    <oos:customerInfo>
      <oos:customer>
        <oos:regNum>03763000194</oos:regNum>
        <oos:fullName>Муниципальное бюджетное учреждение &quot;Межпоселенческий Центр народной культуры Майкопского района&quot;</oos:fullName>
      </oos:customer>
      <oos:OKTMO>
        <oos:code>79622455</oos:code>
        <oos:name>Тульское</oos:name>
      </oos:OKTMO>
    </oos:customerInfo>
    <oos:responsibleContactInfo>
      <oos:lastName>Прокаев</oos:lastName>
      <oos:firstName>Денис</oos:firstName>
      <oos:middleName>Александрович</oos:middleName>
      <oos:phone>8 8777751455</oos:phone>
    </oos:responsibleContactInfo>
    <oos:providedPurchases>
      <oos:positions>
        <oos:position>
          <oos:commonInfo>
            <oos:positionNumber>П44201403763000194000021</oos:positionNumber>
            <oos:amountKBKs>
              <oos:KBK>
                <oos:code>90408010000000000226</oos:code>
                <oos:amount>30000</oos:amount>
              </oos:KBK>
            </oos:amountKBKs>
            <oos:OKVEDs>
              <oos:OKVED>
                <oos:code>92.12</oos:code>
                <oos:name>Прокат фильмов</oos:name>
              </oos:OKVED>
            </oos:OKVEDs>
            <oos:contractSubjectName>прокатная плата</oos:contractSubjectName>
            <oos:contractMaxPrice>30000</oos:contractMaxPrice>
            <oos:payments>30000</oos:payments>
            <oos:contractCurrency>
              <oos:code>RUB</oos:code>
              <oos:name>Российский рубль</oos:name>
            </oos:contractCurrency>
            <oos:placingWay>
              <oos:code>EP44</oos:code>
              <oos:name>Закупка у единственного поставщика (подрядчика, исполнителя)</oos:name>
            </oos:placingWay>
            <oos:positionPublishDate>2014-02-13T15:55:05Z</oos:positionPublishDate>
            <oos:noPublicDiscussion>false</oos:noPublicDiscussion>
          </oos:commonInfo>
          <oos:products>
            <oos:product>
              <oos:OKPD>
                <oos:code/>
              </oos:OKPD>
              <oos:name>прокатная плата</oos:name>
              <oos:internationalName>сокласно договора</oos:internationalName>
              <oos:minRequirement>сокласно договора</oos:minRequirement>
              <oos:OKEI>
                <oos:code/>
              </oos:OKEI>
              <oos:sumMax>30000</oos:sumMax>
              <oos:price>0</oos:price>
              <oos:quantityUndefined>true</oos:quantityUndefined>
            </oos:product>
          </oos:products>
          <oos:purchaseConditions>
            <oos:advance>согласно договора</oos:advance>
            <oos:purchaseGraph>
              <oos:purchasePlacingTerm>
                <oos:month>1</oos:month>
                <oos:year>2014</oos:year>
              </oos:purchasePlacingTerm>
              <oos:contractExecutionTerm>
                <oos:month>12</oos:month>
                <oos:year>2014</oos:year>
              </oos:contractExecutionTerm>
              <oos:contractExecutionStages>согласно договора</oos:contractExecutionStages>
              <oos:periodicity>согласно договора</oos:periodicity>
            </oos:purchaseGraph>
          </oos:purchaseConditions>
        </oos:position>
        <oos:position>
          <oos:commonInfo>
            <oos:positionNumber>П44201403763000194000020</oos:positionNumber>
            <oos:amountKBKs>
              <oos:KBK>
                <oos:code>90408017250140611226</oos:code>
                <oos:amount>35000</oos:amount>
              </oos:KBK>
            </oos:amountKBKs>
            <oos:OKVEDs>
              <oos:OKVED>
                <oos:code>52.45.4</oos:code>
                <oos:name>Розничная торговля техническими носителями информации (с записями и без записей)</oos:name>
              </oos:OKVED>
            </oos:OKVEDs>
            <oos:contractSubjectName>Приобретение огнетушителей</oos:contractSubjectName>
            <oos:contractMaxPrice>35000</oos:contractMaxPrice>
            <oos:payments>35000</oos:payments>
            <oos:contractCurrency>
              <oos:code>RUB</oos:code>
              <oos:name>Российский рубль</oos:name>
            </oos:contractCurrency>
            <oos:placingWay>
              <oos:code>EP44</oos:code>
              <oos:name>Закупка у единственного поставщика (подрядчика, исполнителя)</oos:name>
            </oos:placingWay>
            <oos:positionPublishDate>2014-01-18T19:29:44Z</oos:positionPublishDate>
            <oos:noPublicDiscussion>false</oos:noPublicDiscussion>
          </oos:commonInfo>
          <oos:products>
            <oos:product>
              <oos:OKPD>
                <oos:code/>
              </oos:OKPD>
              <oos:name>Приобретение огнетушителей</oos:name>
              <oos:minRequirement>в соответствии с условиями договора</oos:minRequirement>
              <oos:OKEI>
                <oos:code>796</oos:code>
                <oos:name>Штука</oos:name>
              </oos:OKEI>
              <oos:sumMax>35000</oos:sumMax>
              <oos:price>0</oos:price>
              <oos:quantityUndefined>false</oos:quantityUndefined>
              <oos:quantity>35</oos:quantity>
              <oos:quantityCurrentYear>35</oos:quantityCurrentYear>
            </oos:product>
          </oos:products>
          <oos:purchaseConditions>
            <oos:advance>не указано</oos:advance>
            <oos:purchaseGraph>
              <oos:purchasePlacingTerm>
                <oos:month>1</oos:month>
                <oos:year>2014</oos:year>
              </oos:purchasePlacingTerm>
              <oos:contractExecutionTerm>
                <oos:month>12</oos:month>
                <oos:year>2014</oos:year>
              </oos:contractExecutionTerm>
              <oos:contractExecutionStages>не указано</oos:contractExecutionStages>
              <oos:periodicity>не указано</oos:periodicity>
            </oos:purchaseGraph>
          </oos:purchaseConditions>
        </oos:position>
        <oos:position>
          <oos:commonInfo>
            <oos:positionNumber>П44201403763000194000008</oos:positionNumber>
            <oos:amountKBKs>
              <oos:KBK>
                <oos:code>90408017240100611340</oos:code>
                <oos:amount>50000</oos:amount>
              </oos:KBK>
            </oos:amountKBKs>
            <oos:OKVEDs>
              <oos:OKVED>
                <oos:code>52.44.6</oos:code>
                <oos:name>Розничная торговля бытовыми изделиями и приборами, не включенными в другие группировки</oos:name>
              </oos:OKVED>
            </oos:OKVEDs>
            <oos:contractSubjectName>Приобретение хозяйственных материалов</oos:contractSubjectName>
            <oos:contractMaxPrice>50000</oos:contractMaxPrice>
            <oos:payments>50000</oos:payments>
            <oos:contractCurrency>
              <oos:code>RUB</oos:code>
              <oos:name>Российский рубль</oos:name>
            </oos:contractCurrency>
            <oos:placingWay>
              <oos:code>EP44</oos:code>
              <oos:name>Закупка у единственного поставщика (подрядчика, исполнителя)</oos:name>
            </oos:placingWay>
            <oos:positionPublishDate>2014-01-18T19:29:44Z</oos:positionPublishDate>
            <oos:noPublicDiscussion>false</oos:noPublicDiscussion>
          </oos:commonInfo>
          <oos:products>
            <oos:product>
              <oos:OKPD>
                <oos:code/>
              </oos:OKPD>
              <oos:name>Приобретение хозяйственных материалов</oos:name>
              <oos:minRequirement>Своевременная поставка товара</oos:minRequirement>
              <oos:OKEI>
                <oos:code/>
              </oos:OKEI>
              <oos:sumMax>50000</oos:sumMax>
              <oos:price>0</oos:price>
              <oos:quantityUndefined>true</oos:quantityUndefined>
            </oos:product>
          </oos:products>
          <oos:purchaseConditions>
            <oos:advance>не указано</oos:advance>
            <oos:purchaseGraph>
              <oos:purchasePlacingTerm>
                <oos:month>1</oos:month>
                <oos:year>2014</oos:year>
              </oos:purchasePlacingTerm>
              <oos:contractExecutionTerm>
                <oos:month>12</oos:month>
                <oos:year>2014</oos:year>
              </oos:contractExecutionTerm>
              <oos:contractExecutionStages>не указано</oos:contractExecutionStages>
              <oos:periodicity>не указано</oos:periodicity>
            </oos:purchaseGraph>
          </oos:purchaseConditions>
        </oos:position>
        <oos:position>
          <oos:commonInfo>
            <oos:positionNumber>П44201403763000194000005</oos:positionNumber>
            <oos:amountKBKs>
              <oos:KBK>
                <oos:code>90408017210100611223</oos:code>
                <oos:amount>844200</oos:amount>
              </oos:KBK>
            </oos:amountKBKs>
            <oos:OKVEDs>
              <oos:OKVED>
                <oos:code>40.30.3</oos:code>
                <oos:name>Распределение пара и горячей воды (тепловой энергии)</oos:name>
              </oos:OKVED>
            </oos:OKVEDs>
            <oos:contractSubjectName>Оказание услуги на отпуск тепловой энергии </oos:contractSubjectName>
            <oos:contractMaxPrice>844200</oos:contractMaxPrice>
            <oos:payments>844200</oos:payments>
            <oos:contractCurrency>
              <oos:code>RUB</oos:code>
              <oos:name>Российский рубль</oos:name>
            </oos:contractCurrency>
            <oos:placingWay>
              <oos:code>EP44</oos:code>
              <oos:name>Закупка у единственного поставщика (подрядчика, исполнителя)</oos:name>
            </oos:placingWay>
            <oos:positionPublishDate>2014-01-18T19:29:44Z</oos:positionPublishDate>
            <oos:noPublicDiscussion>false</oos:noPublicDiscussion>
          </oos:commonInfo>
          <oos:products>
            <oos:product>
              <oos:OKPD>
                <oos:code/>
              </oos:OKPD>
              <oos:name>Оказание услуги на отпуск тепловой энергии </oos:name>
              <oos:minRequirement>Бесперебойная поставка тепла</oos:minRequirement>
              <oos:OKEI>
                <oos:code>238</oos:code>
                <oos:name>Гигакалория в час</oos:name>
              </oos:OKEI>
              <oos:sumMax>844200</oos:sumMax>
              <oos:price>0</oos:price>
              <oos:quantityUndefined>false</oos:quantityUndefined>
              <oos:quantity>294</oos:quantity>
              <oos:quantityCurrentYear>294</oos:quantityCurrentYear>
            </oos:product>
          </oos:products>
          <oos:purchaseConditions>
            <oos:advance>не указано</oos:advance>
            <oos:purchaseGraph>
              <oos:purchasePlacingTerm>
                <oos:month>1</oos:month>
                <oos:year>2014</oos:year>
              </oos:purchasePlacingTerm>
              <oos:contractExecutionTerm>
                <oos:month>12</oos:month>
                <oos:year>2014</oos:year>
              </oos:contractExecutionTerm>
              <oos:contractExecutionStages>не указано</oos:contractExecutionStages>
              <oos:periodicity>не указано</oos:periodicity>
            </oos:purchaseGraph>
          </oos:purchaseConditions>
        </oos:position>
        <oos:position>
          <oos:commonInfo>
            <oos:positionNumber>П44201403763000194000010</oos:positionNumber>
            <oos:amountKBKs>
              <oos:KBK>
                <oos:code>90408017240100611221</oos:code>
                <oos:amount>49200</oos:amount>
              </oos:KBK>
            </oos:amountKBKs>
            <oos:OKVEDs>
              <oos:OKVED>
                <oos:code>64.20.11</oos:code>
                <oos:name>Деятельность в области фиксированной телефонной связи</oos:name>
              </oos:OKVED>
            </oos:OKVEDs>
            <oos:contractSubjectName>Услуги по электросвязи</oos:contractSubjectName>
            <oos:contractMaxPrice>49200</oos:contractMaxPrice>
            <oos:payments>49200</oos:payments>
            <oos:contractCurrency>
              <oos:code>RUB</oos:code>
              <oos:name>Российский рубль</oos:name>
            </oos:contractCurrency>
            <oos:placingWay>
              <oos:code>EP44</oos:code>
              <oos:name>Закупка у единственного поставщика (подрядчика, исполнителя)</oos:name>
            </oos:placingWay>
            <oos:positionPublishDate>2014-01-18T19:29:44Z</oos:positionPublishDate>
            <oos:noPublicDiscussion>false</oos:noPublicDiscussion>
          </oos:commonInfo>
          <oos:products>
            <oos:product>
              <oos:OKPD>
                <oos:code/>
              </oos:OKPD>
              <oos:name>Услуги по электросвязи</oos:name>
              <oos:minRequirement>Качественная бесперебойная связь</oos:minRequirement>
              <oos:OKEI>
                <oos:code>796</oos:code>
                <oos:name>Штука</oos:name>
              </oos:OKEI>
              <oos:sumMax>49200</oos:sumMax>
              <oos:price>0</oos:price>
              <oos:quantityUndefined>false</oos:quantityUndefined>
              <oos:quantity>3</oos:quantity>
              <oos:quantityCurrentYear>3</oos:quantityCurrentYear>
            </oos:product>
          </oos:products>
          <oos:purchaseConditions>
            <oos:advance>не указано</oos:advance>
            <oos:purchaseGraph>
              <oos:purchasePlacingTerm>
                <oos:month>1</oos:month>
                <oos:year>2014</oos:year>
              </oos:purchasePlacingTerm>
              <oos:contractExecutionTerm>
                <oos:month>12</oos:month>
                <oos:year>2014</oos:year>
              </oos:contractExecutionTerm>
              <oos:contractExecutionStages>не указано</oos:contractExecutionStages>
              <oos:periodicity>не указано</oos:periodicity>
            </oos:purchaseGraph>
          </oos:purchaseConditions>
        </oos:position>
        <oos:position>
          <oos:commonInfo>
            <oos:positionNumber>П44201403763000194000013</oos:positionNumber>
            <oos:amountKBKs>
              <oos:KBK>
                <oos:code>90408017240100611225</oos:code>
                <oos:amount>5000</oos:amount>
              </oos:KBK>
            </oos:amountKBKs>
            <oos:OKVEDs>
              <oos:OKVED>
                <oos:code>72.22</oos:code>
                <oos:name>Прочая деятельность по разработке программного обеспечения и консультированию в этой области</oos:name>
              </oos:OKVED>
            </oos:OKVEDs>
            <oos:contractSubjectName>Услуги в области управления средствами вычислительной техники</oos:contractSubjectName>
            <oos:contractMaxPrice>5000</oos:contractMaxPrice>
            <oos:payments>5000</oos:payments>
            <oos:contractCurrency>
              <oos:code>RUB</oos:code>
              <oos:name>Российский рубль</oos:name>
            </oos:contractCurrency>
            <oos:placingWay>
              <oos:code>EP44</oos:code>
              <oos:name>Закупка у единственного поставщика (подрядчика, исполнителя)</oos:name>
            </oos:placingWay>
            <oos:positionPublishDate>2014-01-18T19:29:44Z</oos:positionPublishDate>
            <oos:noPublicDiscussion>false</oos:noPublicDiscussion>
          </oos:commonInfo>
          <oos:products>
            <oos:product>
              <oos:OKPD>
                <oos:code/>
              </oos:OKPD>
              <oos:name>Услуги в области управления средствами вычислительной техники</oos:name>
              <oos:minRequirement>В соответствии с условиями договора</oos:minRequirement>
              <oos:OKEI>
                <oos:code/>
              </oos:OKEI>
              <oos:sumMax>5000</oos:sumMax>
              <oos:price>0</oos:price>
              <oos:quantityUndefined>true</oos:quantityUndefined>
            </oos:product>
          </oos:products>
          <oos:purchaseConditions>
            <oos:advance>не указано</oos:advance>
            <oos:purchaseGraph>
              <oos:purchasePlacingTerm>
                <oos:month>1</oos:month>
                <oos:year>2014</oos:year>
              </oos:purchasePlacingTerm>
              <oos:contractExecutionTerm>
                <oos:month>12</oos:month>
                <oos:year>2014</oos:year>
              </oos:contractExecutionTerm>
              <oos:contractExecutionStages>не указано</oos:contractExecutionStages>
              <oos:periodicity>не указано</oos:periodicity>
            </oos:purchaseGraph>
          </oos:purchaseConditions>
        </oos:position>
        <oos:position>
          <oos:commonInfo>
            <oos:positionNumber>П44201403763000194000011</oos:positionNumber>
            <oos:amountKBKs>
              <oos:KBK>
                <oos:code>90408017240120611226</oos:code>
                <oos:amount>32000</oos:amount>
              </oos:KBK>
            </oos:amountKBKs>
            <oos:OKVEDs>
              <oos:OKVED>
                <oos:code>75.24.2</oos:code>
                <oos:name>Деятельность специализированных государственных органов охраны и безопасности</oos:name>
              </oos:OKVED>
            </oos:OKVEDs>
            <oos:contractSubjectName>Расходы на аттестацию рабочих мест</oos:contractSubjectName>
            <oos:contractMaxPrice>32000</oos:contractMaxPrice>
            <oos:payments>32000</oos:payments>
            <oos:contractCurrency>
              <oos:code>RUB</oos:code>
              <oos:name>Российский рубль</oos:name>
            </oos:contractCurrency>
            <oos:placingWay>
              <oos:code>EP44</oos:code>
              <oos:name>Закупка у единственного поставщика (подрядчика, исполнителя)</oos:name>
            </oos:placingWay>
            <oos:positionPublishDate>2014-01-18T19:29:44Z</oos:positionPublishDate>
            <oos:noPublicDiscussion>false</oos:noPublicDiscussion>
          </oos:commonInfo>
          <oos:products>
            <oos:product>
              <oos:OKPD>
                <oos:code/>
              </oos:OKPD>
              <oos:name>Расходы на аттестацию рабочих мест</oos:name>
              <oos:minRequirement>Соответствие стандартам</oos:minRequirement>
              <oos:OKEI>
                <oos:code>796</oos:code>
                <oos:name>Штука</oos:name>
              </oos:OKEI>
              <oos:sumMax>32000</oos:sumMax>
              <oos:price>0</oos:price>
              <oos:quantityUndefined>false</oos:quantityUndefined>
              <oos:quantity>16</oos:quantity>
              <oos:quantityCurrentYear>16</oos:quantityCurrentYear>
            </oos:product>
          </oos:products>
          <oos:purchaseConditions>
            <oos:advance>не указано</oos:advance>
            <oos:purchaseGraph>
              <oos:purchasePlacingTerm>
                <oos:month>1</oos:month>
                <oos:year>2014</oos:year>
              </oos:purchasePlacingTerm>
              <oos:contractExecutionTerm>
                <oos:month>12</oos:month>
                <oos:year>2014</oos:year>
              </oos:contractExecutionTerm>
              <oos:contractExecutionStages>не указано</oos:contractExecutionStages>
              <oos:periodicity>не указано</oos:periodicity>
            </oos:purchaseGraph>
          </oos:purchaseConditions>
        </oos:position>
        <oos:position>
          <oos:commonInfo>
            <oos:positionNumber>П44201403763000194000018</oos:positionNumber>
            <oos:amountKBKs>
              <oos:KBK>
                <oos:code>90408017240120611226</oos:code>
                <oos:amount>57000</oos:amount>
              </oos:KBK>
            </oos:amountKBKs>
            <oos:OKVEDs>
              <oos:OKVED>
                <oos:code>55.30</oos:code>
                <oos:name>Деятельность ресторанов и кафе</oos:name>
              </oos:OKVED>
            </oos:OKVEDs>
            <oos:contractSubjectName>Оказание услуги по организации питания 
</oos:contractSubjectName>
            <oos:contractMaxPrice>57000</oos:contractMaxPrice>
            <oos:payments>57000</oos:payments>
            <oos:contractCurrency>
              <oos:code>RUB</oos:code>
              <oos:name>Российский рубль</oos:name>
            </oos:contractCurrency>
            <oos:placingWay>
              <oos:code>EP44</oos:code>
              <oos:name>Закупка у единственного поставщика (подрядчика, исполнителя)</oos:name>
            </oos:placingWay>
            <oos:positionPublishDate>2014-01-18T19:29:44Z</oos:positionPublishDate>
            <oos:noPublicDiscussion>false</oos:noPublicDiscussion>
          </oos:commonInfo>
          <oos:products>
            <oos:product>
              <oos:OKPD>
                <oos:code/>
              </oos:OKPD>
              <oos:name>Оказание услуги по организации питания 
</oos:name>
              <oos:minRequirement>Согласно условиям договора</oos:minRequirement>
              <oos:OKEI>
                <oos:code/>
              </oos:OKEI>
              <oos:sumMax>57000</oos:sumMax>
              <oos:price>0</oos:price>
              <oos:quantityUndefined>true</oos:quantityUndefined>
            </oos:product>
          </oos:products>
          <oos:purchaseConditions>
            <oos:advance>не указано</oos:advance>
            <oos:purchaseGraph>
              <oos:purchasePlacingTerm>
                <oos:month>1</oos:month>
                <oos:year>2014</oos:year>
              </oos:purchasePlacingTerm>
              <oos:contractExecutionTerm>
                <oos:month>12</oos:month>
                <oos:year>2014</oos:year>
              </oos:contractExecutionTerm>
              <oos:contractExecutionStages>не указано</oos:contractExecutionStages>
              <oos:periodicity>не указано</oos:periodicity>
            </oos:purchaseGraph>
          </oos:purchaseConditions>
        </oos:position>
        <oos:position>
          <oos:commonInfo>
            <oos:positionNumber>П44201403763000194000006</oos:positionNumber>
            <oos:amountKBKs>
              <oos:KBK>
                <oos:code>90408017210100611223</oos:code>
                <oos:amount>79000</oos:amount>
              </oos:KBK>
            </oos:amountKBKs>
            <oos:OKVEDs>
              <oos:OKVED>
                <oos:code>41.00.2</oos:code>
                <oos:name>Распределение воды</oos:name>
              </oos:OKVED>
            </oos:OKVEDs>
            <oos:contractSubjectName>Оказание услуги на отпуск газа</oos:contractSubjectName>
            <oos:contractMaxPrice>79000</oos:contractMaxPrice>
            <oos:payments>79000</oos:payments>
            <oos:contractCurrency>
              <oos:code>RUB</oos:code>
              <oos:name>Российский рубль</oos:name>
            </oos:contractCurrency>
            <oos:placingWay>
              <oos:code>EP44</oos:code>
              <oos:name>Закупка у единственного поставщика (подрядчика, исполнителя)</oos:name>
            </oos:placingWay>
            <oos:positionPublishDate>2014-01-18T19:29:44Z</oos:positionPublishDate>
            <oos:noPublicDiscussion>false</oos:noPublicDiscussion>
          </oos:commonInfo>
          <oos:products>
            <oos:product>
              <oos:OKPD>
                <oos:code/>
              </oos:OKPD>
              <oos:name>Оказание услуги на отпуск газа</oos:name>
              <oos:minRequirement>Бесперебойная поставка газа</oos:minRequirement>
              <oos:OKEI>
                <oos:code>113</oos:code>
                <oos:name>Кубический метр</oos:name>
              </oos:OKEI>
              <oos:sumMax>79000</oos:sumMax>
              <oos:price>0</oos:price>
              <oos:quantityUndefined>false</oos:quantityUndefined>
              <oos:quantity>13</oos:quantity>
              <oos:quantityCurrentYear>13</oos:quantityCurrentYear>
            </oos:product>
          </oos:products>
          <oos:purchaseConditions>
            <oos:advance>не указано</oos:advance>
            <oos:purchaseGraph>
              <oos:purchasePlacingTerm>
                <oos:month>1</oos:month>
                <oos:year>2014</oos:year>
              </oos:purchasePlacingTerm>
              <oos:contractExecutionTerm>
                <oos:month>12</oos:month>
                <oos:year>2014</oos:year>
              </oos:contractExecutionTerm>
              <oos:contractExecutionStages>не указано</oos:contractExecutionStages>
              <oos:periodicity>не указано</oos:periodicity>
            </oos:purchaseGraph>
          </oos:purchaseConditions>
        </oos:position>
        <oos:position>
          <oos:commonInfo>
            <oos:positionNumber>П44201403763000194000009</oos:positionNumber>
            <oos:amountKBKs>
              <oos:KBK>
                <oos:code>90408017240100611226</oos:code>
                <oos:amount>1200</oos:amount>
              </oos:KBK>
            </oos:amountKBKs>
            <oos:OKVEDs>
              <oos:OKVED>
                <oos:code>72.60</oos:code>
                <oos:name>Прочая деятельность, связанная с использованием вычислительной техники и информационных технологий</oos:name>
              </oos:OKVED>
            </oos:OKVEDs>
            <oos:contractSubjectName>Услуги по выдаче сертификатов соответствия продукции установленным Приобретение Cертификатов на техническую поддержку Программного обеспечения </oos:contractSubjectName>
            <oos:contractMaxPrice>1200</oos:contractMaxPrice>
            <oos:payments>1200</oos:payments>
            <oos:contractCurrency>
              <oos:code>RUB</oos:code>
              <oos:name>Российский рубль</oos:name>
            </oos:contractCurrency>
            <oos:placingWay>
              <oos:code>EP44</oos:code>
              <oos:name>Закупка у единственного поставщика (подрядчика, исполнителя)</oos:name>
            </oos:placingWay>
            <oos:positionPublishDate>2014-01-18T19:29:44Z</oos:positionPublishDate>
            <oos:noPublicDiscussion>false</oos:noPublicDiscussion>
          </oos:commonInfo>
          <oos:products>
            <oos:product>
              <oos:OKPD>
                <oos:code/>
              </oos:OKPD>
              <oos:name>Услуги по выдаче сертификатов соответствия продукции установленным Приобретение Cертификатов на техническую поддержку Программного обеспечения </oos:name>
              <oos:minRequirement>Качественное бесперебойное обслуживание</oos:minRequirement>
              <oos:OKEI>
                <oos:code>796</oos:code>
                <oos:name>Штука</oos:name>
              </oos:OKEI>
              <oos:sumMax>1200</oos:sumMax>
              <oos:price>0</oos:price>
              <oos:quantityUndefined>false</oos:quantityUndefined>
              <oos:quantity>1</oos:quantity>
              <oos:quantityCurrentYear>1</oos:quantityCurrentYear>
            </oos:product>
          </oos:products>
          <oos:purchaseConditions>
            <oos:advance>не указано</oos:advance>
            <oos:purchaseGraph>
              <oos:purchasePlacingTerm>
                <oos:month>1</oos:month>
                <oos:year>2014</oos:year>
              </oos:purchasePlacingTerm>
              <oos:contractExecutionTerm>
                <oos:month>12</oos:month>
                <oos:year>2014</oos:year>
              </oos:contractExecutionTerm>
              <oos:contractExecutionStages>не указано</oos:contractExecutionStages>
              <oos:periodicity>не указано</oos:periodicity>
            </oos:purchaseGraph>
          </oos:purchaseConditions>
        </oos:position>
        <oos:position>
          <oos:commonInfo>
            <oos:positionNumber>П44201403763000194000001</oos:positionNumber>
            <oos:amountKBKs>
              <oos:KBK>
                <oos:code>90408017210100611340</oos:code>
                <oos:amount>20000</oos:amount>
              </oos:KBK>
            </oos:amountKBKs>
            <oos:OKVEDs>
              <oos:OKVED>
                <oos:code>21.23</oos:code>
                <oos:name>Производство писчебумажных изделий</oos:name>
              </oos:OKVED>
            </oos:OKVEDs>
            <oos:contractSubjectName>Приобритение бумаги</oos:contractSubjectName>
            <oos:contractMaxPrice>20000</oos:contractMaxPrice>
            <oos:payments>20000</oos:payments>
            <oos:contractCurrency>
              <oos:code>RUB</oos:code>
              <oos:name>Российский рубль</oos:name>
            </oos:contractCurrency>
            <oos:placingWay>
              <oos:code>EP44</oos:code>
              <oos:name>Закупка у единственного поставщика (подрядчика, исполнителя)</oos:name>
            </oos:placingWay>
            <oos:positionPublishDate>2014-01-18T19:29:44Z</oos:positionPublishDate>
            <oos:noPublicDiscussion>false</oos:noPublicDiscussion>
          </oos:commonInfo>
          <oos:products>
            <oos:product>
              <oos:OKPD>
                <oos:code/>
              </oos:OKPD>
              <oos:name>Приобритение бумаги</oos:name>
              <oos:minRequirement>Бумага для офисной техники</oos:minRequirement>
              <oos:OKEI>
                <oos:code>796</oos:code>
                <oos:name>Штука</oos:name>
              </oos:OKEI>
              <oos:sumMax>20000</oos:sumMax>
              <oos:price>0</oos:price>
              <oos:quantityUndefined>false</oos:quantityUndefined>
              <oos:quantity>117</oos:quantity>
              <oos:quantityCurrentYear>117</oos:quantityCurrentYear>
            </oos:product>
          </oos:products>
          <oos:purchaseConditions>
            <oos:advance>не указано</oos:advance>
            <oos:purchaseGraph>
              <oos:purchasePlacingTerm>
                <oos:month>1</oos:month>
                <oos:year>2014</oos:year>
              </oos:purchasePlacingTerm>
              <oos:contractExecutionTerm>
                <oos:month>12</oos:month>
                <oos:year>2014</oos:year>
              </oos:contractExecutionTerm>
              <oos:contractExecutionStages>не указано</oos:contractExecutionStages>
              <oos:periodicity>не указано</oos:periodicity>
            </oos:purchaseGraph>
          </oos:purchaseConditions>
        </oos:position>
        <oos:position>
          <oos:commonInfo>
            <oos:positionNumber>П44201403763000194000014</oos:positionNumber>
            <oos:amountKBKs>
              <oos:KBK>
                <oos:code>90408017240100611225</oos:code>
                <oos:amount>162000</oos:amount>
              </oos:KBK>
            </oos:amountKBKs>
            <oos:OKVEDs>
              <oos:OKVED>
                <oos:code>74.84</oos:code>
                <oos:name>Предоставление прочих услуг</oos:name>
              </oos:OKVED>
            </oos:OKVEDs>
            <oos:contractSubjectName>Техническое обслуживание пожарной, охранной сигнализации</oos:contractSubjectName>
            <oos:contractMaxPrice>162000</oos:contractMaxPrice>
            <oos:payments>162000</oos:payments>
            <oos:contractCurrency>
              <oos:code>RUB</oos:code>
              <oos:name>Российский рубль</oos:name>
            </oos:contractCurrency>
            <oos:placingWay>
              <oos:code>EP44</oos:code>
              <oos:name>Закупка у единственного поставщика (подрядчика, исполнителя)</oos:name>
            </oos:placingWay>
            <oos:positionPublishDate>2014-01-18T19:29:44Z</oos:positionPublishDate>
            <oos:noPublicDiscussion>false</oos:noPublicDiscussion>
          </oos:commonInfo>
          <oos:products>
            <oos:product>
              <oos:OKPD>
                <oos:code/>
              </oos:OKPD>
              <oos:name>Техническое обслуживание пожарной, охранной сигнализации</oos:name>
              <oos:minRequirement>Своевременное обслуживание</oos:minRequirement>
              <oos:OKEI>
                <oos:code>796</oos:code>
                <oos:name>Штука</oos:name>
              </oos:OKEI>
              <oos:sumMax>162000</oos:sumMax>
              <oos:price>0</oos:price>
              <oos:quantityUndefined>false</oos:quantityUndefined>
              <oos:quantity>4</oos:quantity>
              <oos:quantityCurrentYear>4</oos:quantityCurrentYear>
            </oos:product>
          </oos:products>
          <oos:purchaseConditions>
            <oos:advance>не указано</oos:advance>
            <oos:purchaseGraph>
              <oos:purchasePlacingTerm>
                <oos:month>1</oos:month>
                <oos:year>2014</oos:year>
              </oos:purchasePlacingTerm>
              <oos:contractExecutionTerm>
                <oos:month>12</oos:month>
                <oos:year>2014</oos:year>
              </oos:contractExecutionTerm>
              <oos:contractExecutionStages>не указано</oos:contractExecutionStages>
              <oos:periodicity>не указано</oos:periodicity>
            </oos:purchaseGraph>
          </oos:purchaseConditions>
        </oos:position>
        <oos:position>
          <oos:commonInfo>
            <oos:positionNumber>П44201403763000194000004</oos:positionNumber>
            <oos:amountKBKs>
              <oos:KBK>
                <oos:code>90408017210100611223</oos:code>
                <oos:amount>27000</oos:amount>
              </oos:KBK>
            </oos:amountKBKs>
            <oos:OKVEDs>
              <oos:OKVED>
                <oos:code>41.00.2</oos:code>
                <oos:name>Распределение воды</oos:name>
              </oos:OKVED>
            </oos:OKVEDs>
            <oos:contractSubjectName>Оказание услуги на отпуск питьевой воды и приема сточных вод </oos:contractSubjectName>
            <oos:contractMaxPrice>27000</oos:contractMaxPrice>
            <oos:payments>27000</oos:payments>
            <oos:contractCurrency>
              <oos:code>RUB</oos:code>
              <oos:name>Российский рубль</oos:name>
            </oos:contractCurrency>
            <oos:placingWay>
              <oos:code>EP44</oos:code>
              <oos:name>Закупка у единственного поставщика (подрядчика, исполнителя)</oos:name>
            </oos:placingWay>
            <oos:positionPublishDate>2014-01-18T19:29:44Z</oos:positionPublishDate>
            <oos:noPublicDiscussion>false</oos:noPublicDiscussion>
          </oos:commonInfo>
          <oos:products>
            <oos:product>
              <oos:OKPD>
                <oos:code/>
              </oos:OKPD>
              <oos:name>Оказание услуги на отпуск питьевой воды и приема сточных вод </oos:name>
              <oos:minRequirement>Бесперебойное водоснабжение</oos:minRequirement>
              <oos:OKEI>
                <oos:code>113</oos:code>
                <oos:name>Кубический метр</oos:name>
              </oos:OKEI>
              <oos:sumMax>27000</oos:sumMax>
              <oos:price>0</oos:price>
              <oos:quantityUndefined>false</oos:quantityUndefined>
              <oos:quantity>1200</oos:quantity>
              <oos:quantityCurrentYear>1200</oos:quantityCurrentYear>
            </oos:product>
          </oos:products>
          <oos:purchaseConditions>
            <oos:advance>не указано</oos:advance>
            <oos:purchaseGraph>
              <oos:purchasePlacingTerm>
                <oos:month>1</oos:month>
                <oos:year>2014</oos:year>
              </oos:purchasePlacingTerm>
              <oos:contractExecutionTerm>
                <oos:month>12</oos:month>
                <oos:year>2014</oos:year>
              </oos:contractExecutionTerm>
              <oos:contractExecutionStages>не указано</oos:contractExecutionStages>
              <oos:periodicity>не указано</oos:periodicity>
            </oos:purchaseGraph>
          </oos:purchaseConditions>
        </oos:position>
        <oos:position>
          <oos:commonInfo>
            <oos:positionNumber>П44201403763000194000017</oos:positionNumber>
            <oos:amountKBKs>
              <oos:KBK>
                <oos:code>90408017240100611226</oos:code>
                <oos:amount>2000</oos:amount>
              </oos:KBK>
            </oos:amountKBKs>
            <oos:OKVEDs>
              <oos:OKVED>
                <oos:code>74.70.3</oos:code>
                <oos:name>Деятельность по проведению дезинфекционных, дезинсекционных и дератизационных работ</oos:name>
              </oos:OKVED>
            </oos:OKVEDs>
            <oos:contractSubjectName>Оплата информационных услуг (выполнение расчетов по платежам за выбросы вредных веществ в атмосферу)</oos:contractSubjectName>
            <oos:contractMaxPrice>2000</oos:contractMaxPrice>
            <oos:payments>2000</oos:payments>
            <oos:contractCurrency>
              <oos:code>RUB</oos:code>
              <oos:name>Российский рубль</oos:name>
            </oos:contractCurrency>
            <oos:placingWay>
              <oos:code>EP44</oos:code>
              <oos:name>Закупка у единственного поставщика (подрядчика, исполнителя)</oos:name>
            </oos:placingWay>
            <oos:positionPublishDate>2014-01-18T19:29:44Z</oos:positionPublishDate>
            <oos:noPublicDiscussion>false</oos:noPublicDiscussion>
          </oos:commonInfo>
          <oos:products>
            <oos:product>
              <oos:OKPD>
                <oos:code/>
              </oos:OKPD>
              <oos:name>Оплата информационных услуг (выполнение расчетов по платежам за выбросы вредных веществ в атмосферу)</oos:name>
              <oos:minRequirement>Выполнение расчетов по платежам за выбросы вредных веществ в атмосферу</oos:minRequirement>
              <oos:OKEI>
                <oos:code>876</oos:code>
                <oos:name>Условная единица</oos:name>
              </oos:OKEI>
              <oos:sumMax>2000</oos:sumMax>
              <oos:price>0</oos:price>
              <oos:quantityUndefined>false</oos:quantityUndefined>
              <oos:quantity>4</oos:quantity>
              <oos:quantityCurrentYear>4</oos:quantityCurrentYear>
            </oos:product>
          </oos:products>
          <oos:purchaseConditions>
            <oos:advance>не указано</oos:advance>
            <oos:purchaseGraph>
              <oos:purchasePlacingTerm>
                <oos:month>1</oos:month>
                <oos:year>2014</oos:year>
              </oos:purchasePlacingTerm>
              <oos:contractExecutionTerm>
                <oos:month>12</oos:month>
                <oos:year>2014</oos:year>
              </oos:contractExecutionTerm>
              <oos:contractExecutionStages>не указано</oos:contractExecutionStages>
              <oos:periodicity>не указано</oos:periodicity>
            </oos:purchaseGraph>
          </oos:purchaseConditions>
        </oos:position>
        <oos:position>
          <oos:commonInfo>
            <oos:positionNumber>П44201403763000194000003</oos:positionNumber>
            <oos:amountKBKs>
              <oos:KBK>
                <oos:code>90408017210100611223</oos:code>
                <oos:amount>497000</oos:amount>
              </oos:KBK>
            </oos:amountKBKs>
            <oos:OKVEDs>
              <oos:OKVED>
                <oos:code>40.10.3</oos:code>
                <oos:name>Распределение электроэнергии</oos:name>
              </oos:OKVED>
            </oos:OKVEDs>
            <oos:contractSubjectName>Оказание услуги на поставку электроэнергии </oos:contractSubjectName>
            <oos:contractMaxPrice>497000</oos:contractMaxPrice>
            <oos:payments>497000</oos:payments>
            <oos:contractCurrency>
              <oos:code>RUB</oos:code>
              <oos:name>Российский рубль</oos:name>
            </oos:contractCurrency>
            <oos:placingWay>
              <oos:code>EP44</oos:code>
              <oos:name>Закупка у единственного поставщика (подрядчика, исполнителя)</oos:name>
            </oos:placingWay>
            <oos:positionPublishDate>2014-01-18T19:29:44Z</oos:positionPublishDate>
            <oos:noPublicDiscussion>false</oos:noPublicDiscussion>
          </oos:commonInfo>
          <oos:products>
            <oos:product>
              <oos:OKPD>
                <oos:code/>
              </oos:OKPD>
              <oos:name>Оказание услуги на поставку электроэнергии </oos:name>
              <oos:minRequirement>Бесперебойное энергоснабжение</oos:minRequirement>
              <oos:OKEI>
                <oos:code>214</oos:code>
                <oos:name>Киловатт</oos:name>
              </oos:OKEI>
              <oos:sumMax>497000</oos:sumMax>
              <oos:price>0</oos:price>
              <oos:quantityUndefined>false</oos:quantityUndefined>
              <oos:quantity>77000</oos:quantity>
              <oos:quantityCurrentYear>77000</oos:quantityCurrentYear>
            </oos:product>
          </oos:products>
          <oos:purchaseConditions>
            <oos:advance>не указано</oos:advance>
            <oos:purchaseGraph>
              <oos:purchasePlacingTerm>
                <oos:month>1</oos:month>
                <oos:year>2014</oos:year>
              </oos:purchasePlacingTerm>
              <oos:contractExecutionTerm>
                <oos:month>12</oos:month>
                <oos:year>2014</oos:year>
              </oos:contractExecutionTerm>
              <oos:contractExecutionStages>не указано</oos:contractExecutionStages>
              <oos:periodicity>не указано</oos:periodicity>
            </oos:purchaseGraph>
          </oos:purchaseConditions>
        </oos:position>
        <oos:position>
          <oos:commonInfo>
            <oos:positionNumber>П44201403763000194000007</oos:positionNumber>
            <oos:amountKBKs>
              <oos:KBK>
                <oos:code>90408017210100611225</oos:code>
                <oos:amount>18000</oos:amount>
              </oos:KBK>
            </oos:amountKBKs>
            <oos:OKVEDs>
              <oos:OKVED>
                <oos:code>45.31</oos:code>
                <oos:name>Производство электромонтажных работ</oos:name>
              </oos:OKVED>
            </oos:OKVEDs>
            <oos:contractSubjectName>Услуги по техническому обслуживанию приборов учета расхода пара и горячей воды (тепловой энергии)</oos:contractSubjectName>
            <oos:contractMaxPrice>18000</oos:contractMaxPrice>
            <oos:payments>18000</oos:payments>
            <oos:contractCurrency>
              <oos:code>RUB</oos:code>
              <oos:name>Российский рубль</oos:name>
            </oos:contractCurrency>
            <oos:placingWay>
              <oos:code>EP44</oos:code>
              <oos:name>Закупка у единственного поставщика (подрядчика, исполнителя)</oos:name>
            </oos:placingWay>
            <oos:positionPublishDate>2014-01-18T19:29:44Z</oos:positionPublishDate>
            <oos:noPublicDiscussion>false</oos:noPublicDiscussion>
          </oos:commonInfo>
          <oos:products>
            <oos:product>
              <oos:OKPD>
                <oos:code/>
              </oos:OKPD>
              <oos:name>Услуги по техническому обслуживанию приборов учета расхода пара и горячей воды (тепловой энергии)</oos:name>
              <oos:minRequirement>В соответствии с условиями договора</oos:minRequirement>
              <oos:OKEI>
                <oos:code>796</oos:code>
                <oos:name>Штука</oos:name>
              </oos:OKEI>
              <oos:sumMax>18000</oos:sumMax>
              <oos:price>0</oos:price>
              <oos:quantityUndefined>false</oos:quantityUndefined>
              <oos:quantity>4</oos:quantity>
              <oos:quantityCurrentYear>4</oos:quantityCurrentYear>
            </oos:product>
          </oos:products>
          <oos:purchaseConditions>
            <oos:advance>не указано</oos:advance>
            <oos:purchaseGraph>
              <oos:purchasePlacingTerm>
                <oos:month>1</oos:month>
                <oos:year>2014</oos:year>
              </oos:purchasePlacingTerm>
              <oos:contractExecutionTerm>
                <oos:month>12</oos:month>
                <oos:year>2014</oos:year>
              </oos:contractExecutionTerm>
              <oos:contractExecutionStages>не указано</oos:contractExecutionStages>
              <oos:periodicity>не указано</oos:periodicity>
            </oos:purchaseGraph>
          </oos:purchaseConditions>
        </oos:position>
        <oos:position>
          <oos:commonInfo>
            <oos:positionNumber>П44201403763000194000012</oos:positionNumber>
            <oos:amountKBKs>
              <oos:KBK>
                <oos:code>90408017240100611221</oos:code>
                <oos:amount>10000</oos:amount>
              </oos:KBK>
            </oos:amountKBKs>
            <oos:OKVEDs>
              <oos:OKVED>
                <oos:code>74.84</oos:code>
                <oos:name>Предоставление прочих услуг</oos:name>
              </oos:OKVED>
            </oos:OKVEDs>
            <oos:contractSubjectName>Услуга по аварийному и техническому обслуживанию газового оборудования</oos:contractSubjectName>
            <oos:contractMaxPrice>10000</oos:contractMaxPrice>
            <oos:payments>10000</oos:payments>
            <oos:contractCurrency>
              <oos:code>RUB</oos:code>
              <oos:name>Российский рубль</oos:name>
            </oos:contractCurrency>
            <oos:placingWay>
              <oos:code>EP44</oos:code>
              <oos:name>Закупка у единственного поставщика (подрядчика, исполнителя)</oos:name>
            </oos:placingWay>
            <oos:positionPublishDate>2014-01-18T19:29:44Z</oos:positionPublishDate>
            <oos:noPublicDiscussion>false</oos:noPublicDiscussion>
          </oos:commonInfo>
          <oos:products>
            <oos:product>
              <oos:OKPD>
                <oos:code/>
              </oos:OKPD>
              <oos:name>Услуга по аварийному и техническому обслуживанию газового оборудования</oos:name>
              <oos:minRequirement>В соответствии с условиями договора</oos:minRequirement>
              <oos:OKEI>
                <oos:code>796</oos:code>
                <oos:name>Штука</oos:name>
              </oos:OKEI>
              <oos:sumMax>10000</oos:sumMax>
              <oos:price>0</oos:price>
              <oos:quantityUndefined>false</oos:quantityUndefined>
              <oos:quantity>1</oos:quantity>
              <oos:quantityCurrentYear>1</oos:quantityCurrentYear>
            </oos:product>
          </oos:products>
          <oos:purchaseConditions>
            <oos:advance>не указано</oos:advance>
            <oos:purchaseGraph>
              <oos:purchasePlacingTerm>
                <oos:month>1</oos:month>
                <oos:year>2014</oos:year>
              </oos:purchasePlacingTerm>
              <oos:contractExecutionTerm>
                <oos:month>12</oos:month>
                <oos:year>2014</oos:year>
              </oos:contractExecutionTerm>
              <oos:contractExecutionStages>не указано</oos:contractExecutionStages>
              <oos:periodicity>не указано</oos:periodicity>
            </oos:purchaseGraph>
          </oos:purchaseConditions>
        </oos:position>
        <oos:position>
          <oos:commonInfo>
            <oos:positionNumber>П44201403763000194000019</oos:positionNumber>
            <oos:amountKBKs>
              <oos:KBK>
                <oos:code>90408017240120611226</oos:code>
                <oos:amount>32000</oos:amount>
              </oos:KBK>
            </oos:amountKBKs>
            <oos:OKVEDs>
              <oos:OKVED>
                <oos:code>92.34</oos:code>
                <oos:name>Прочая зрелищно-развлекательная деятельность</oos:name>
              </oos:OKVED>
            </oos:OKVEDs>
            <oos:contractSubjectName>Услуги по организаци и проведение мероприятий</oos:contractSubjectName>
            <oos:contractMaxPrice>32000</oos:contractMaxPrice>
            <oos:payments>32000</oos:payments>
            <oos:contractCurrency>
              <oos:code>RUB</oos:code>
              <oos:name>Российский рубль</oos:name>
            </oos:contractCurrency>
            <oos:placingWay>
              <oos:code>EP44</oos:code>
              <oos:name>Закупка у единственного поставщика (подрядчика, исполнителя)</oos:name>
            </oos:placingWay>
            <oos:positionPublishDate>2014-01-18T19:29:44Z</oos:positionPublishDate>
            <oos:noPublicDiscussion>false</oos:noPublicDiscussion>
          </oos:commonInfo>
          <oos:products>
            <oos:product>
              <oos:OKPD>
                <oos:code/>
              </oos:OKPD>
              <oos:name>Услуги по организаци и проведение мероприятий</oos:name>
              <oos:minRequirement>в соответствии с условиями договора</oos:minRequirement>
              <oos:OKEI>
                <oos:code/>
              </oos:OKEI>
              <oos:sumMax>32000</oos:sumMax>
              <oos:price>0</oos:price>
              <oos:quantityUndefined>true</oos:quantityUndefined>
            </oos:product>
          </oos:products>
          <oos:purchaseConditions>
            <oos:advance>не указано</oos:advance>
            <oos:purchaseGraph>
              <oos:purchasePlacingTerm>
                <oos:month>1</oos:month>
                <oos:year>2014</oos:year>
              </oos:purchasePlacingTerm>
              <oos:contractExecutionTerm>
                <oos:month>12</oos:month>
                <oos:year>2014</oos:year>
              </oos:contractExecutionTerm>
              <oos:contractExecutionStages>не указано</oos:contractExecutionStages>
              <oos:periodicity>не указано</oos:periodicity>
            </oos:purchaseGraph>
          </oos:purchaseConditions>
        </oos:position>
        <oos:position>
          <oos:commonInfo>
            <oos:positionNumber>П44201403763000194000002</oos:positionNumber>
            <oos:amountKBKs>
              <oos:KBK>
                <oos:code>90408017210100611340</oos:code>
                <oos:amount>30000</oos:amount>
              </oos:KBK>
            </oos:amountKBKs>
            <oos:OKVEDs>
              <oos:OKVED>
                <oos:code>52.47.3</oos:code>
                <oos:name>Розничная торговля писчебумажными и канцелярскими товарами</oos:name>
              </oos:OKVED>
            </oos:OKVEDs>
            <oos:contractSubjectName>Приобретение канцелярскиех товаров</oos:contractSubjectName>
            <oos:contractMaxPrice>30000</oos:contractMaxPrice>
            <oos:payments>30000</oos:payments>
            <oos:contractCurrency>
              <oos:code>RUB</oos:code>
              <oos:name>Российский рубль</oos:name>
            </oos:contractCurrency>
            <oos:placingWay>
              <oos:code>EP44</oos:code>
              <oos:name>Закупка у единственного поставщика (подрядчика, исполнителя)</oos:name>
            </oos:placingWay>
            <oos:positionPublishDate>2014-01-18T19:29:44Z</oos:positionPublishDate>
            <oos:noPublicDiscussion>false</oos:noPublicDiscussion>
          </oos:commonInfo>
          <oos:products>
            <oos:product>
              <oos:OKPD>
                <oos:code/>
              </oos:OKPD>
              <oos:name>Приобретение канцелярскиех товаров</oos:name>
              <oos:minRequirement>Своевременная поставка товара</oos:minRequirement>
              <oos:OKEI>
                <oos:code/>
              </oos:OKEI>
              <oos:sumMax>30000</oos:sumMax>
              <oos:price>0</oos:price>
              <oos:quantityUndefined>true</oos:quantityUndefined>
            </oos:product>
          </oos:products>
          <oos:purchaseConditions>
            <oos:advance>не указано</oos:advance>
            <oos:purchaseGraph>
              <oos:purchasePlacingTerm>
                <oos:month>1</oos:month>
                <oos:year>2014</oos:year>
              </oos:purchasePlacingTerm>
              <oos:contractExecutionTerm>
                <oos:month>12</oos:month>
                <oos:year>2014</oos:year>
              </oos:contractExecutionTerm>
              <oos:contractExecutionStages>не указано</oos:contractExecutionStages>
              <oos:periodicity>не указано</oos:periodicity>
            </oos:purchaseGraph>
          </oos:purchaseConditions>
        </oos:position>
        <oos:position>
          <oos:commonInfo>
            <oos:positionNumber>П44201403763000194000015</oos:positionNumber>
            <oos:amountKBKs>
              <oos:KBK>
                <oos:code>90408017240120611226</oos:code>
                <oos:amount>22000</oos:amount>
              </oos:KBK>
            </oos:amountKBKs>
            <oos:OKVEDs>
              <oos:OKVED>
                <oos:code>72.22</oos:code>
                <oos:name>Прочая деятельность по разработке программного обеспечения и консультированию в этой области</oos:name>
              </oos:OKVED>
            </oos:OKVEDs>
            <oos:contractSubjectName>Услуга, связанная с использованием вычислительной техники и информационных технологий. Лицензированная программа по использованию ЭЦП</oos:contractSubjectName>
            <oos:contractMaxPrice>22000</oos:contractMaxPrice>
            <oos:payments>22000</oos:payments>
            <oos:contractCurrency>
              <oos:code>RUB</oos:code>
              <oos:name>Российский рубль</oos:name>
            </oos:contractCurrency>
            <oos:placingWay>
              <oos:code>EP44</oos:code>
              <oos:name>Закупка у единственного поставщика (подрядчика, исполнителя)</oos:name>
            </oos:placingWay>
            <oos:positionPublishDate>2014-01-18T19:29:44Z</oos:positionPublishDate>
            <oos:noPublicDiscussion>false</oos:noPublicDiscussion>
          </oos:commonInfo>
          <oos:products>
            <oos:product>
              <oos:OKPD>
                <oos:code/>
              </oos:OKPD>
              <oos:name>Услуга, связанная с использованием вычислительной техники и информационных технологий. Лицензированная программа по использованию ЭЦП</oos:name>
              <oos:minRequirement>В соответствии с условиями договора</oos:minRequirement>
              <oos:OKEI>
                <oos:code>796</oos:code>
                <oos:name>Штука</oos:name>
              </oos:OKEI>
              <oos:sumMax>22000</oos:sumMax>
              <oos:price>0</oos:price>
              <oos:quantityUndefined>false</oos:quantityUndefined>
              <oos:quantity>5</oos:quantity>
              <oos:quantityCurrentYear>5</oos:quantityCurrentYear>
            </oos:product>
          </oos:products>
          <oos:purchaseConditions>
            <oos:advance>не указано</oos:advance>
            <oos:purchaseGraph>
              <oos:purchasePlacingTerm>
                <oos:month>1</oos:month>
                <oos:year>2014</oos:year>
              </oos:purchasePlacingTerm>
              <oos:contractExecutionTerm>
                <oos:month>12</oos:month>
                <oos:year>2014</oos:year>
              </oos:contractExecutionTerm>
              <oos:contractExecutionStages>не указано</oos:contractExecutionStages>
              <oos:periodicity>не указано</oos:periodicity>
            </oos:purchaseGraph>
          </oos:purchaseConditions>
        </oos:position>
        <oos:position>
          <oos:commonInfo>
            <oos:positionNumber>П44201403763000194000016</oos:positionNumber>
            <oos:amountKBKs>
              <oos:KBK>
                <oos:code>90408017240100611226</oos:code>
                <oos:amount>22000</oos:amount>
              </oos:KBK>
            </oos:amountKBKs>
            <oos:OKVEDs>
              <oos:OKVED>
                <oos:code>90.00.2</oos:code>
                <oos:name>Удаление и обработка твердых отходов</oos:name>
              </oos:OKVED>
            </oos:OKVEDs>
            <oos:contractSubjectName>Услуги по сбору, вывозу мусора и твердых бытовых отходов</oos:contractSubjectName>
            <oos:contractMaxPrice>22000</oos:contractMaxPrice>
            <oos:payments>22000</oos:payments>
            <oos:contractCurrency>
              <oos:code>RUB</oos:code>
              <oos:name>Российский рубль</oos:name>
            </oos:contractCurrency>
            <oos:placingWay>
              <oos:code>EP44</oos:code>
              <oos:name>Закупка у единственного поставщика (подрядчика, исполнителя)</oos:name>
            </oos:placingWay>
            <oos:positionPublishDate>2014-01-18T19:29:44Z</oos:positionPublishDate>
            <oos:noPublicDiscussion>false</oos:noPublicDiscussion>
          </oos:commonInfo>
          <oos:products>
            <oos:product>
              <oos:OKPD>
                <oos:code/>
              </oos:OKPD>
              <oos:name>Услуги по сбору, вывозу мусора и твердых бытовых отходов</oos:name>
              <oos:minRequirement>В соответствии с техническими требованиями</oos:minRequirement>
              <oos:OKEI>
                <oos:code>113</oos:code>
                <oos:name>Кубический метр</oos:name>
              </oos:OKEI>
              <oos:sumMax>22000</oos:sumMax>
              <oos:price>0</oos:price>
              <oos:quantityUndefined>false</oos:quantityUndefined>
              <oos:quantity>60</oos:quantity>
              <oos:quantityCurrentYear>60</oos:quantityCurrentYear>
            </oos:product>
          </oos:products>
          <oos:purchaseConditions>
            <oos:advance>не указано</oos:advance>
            <oos:purchaseGraph>
              <oos:purchasePlacingTerm>
                <oos:month>1</oos:month>
                <oos:year>2014</oos:year>
              </oos:purchasePlacingTerm>
              <oos:contractExecutionTerm>
                <oos:month>12</oos:month>
                <oos:year>2014</oos:year>
              </oos:contractExecutionTerm>
              <oos:contractExecutionStages>не указано</oos:contractExecutionStages>
              <oos:periodicity>не указано</oos:periodicity>
            </oos:purchaseGraph>
          </oos:purchaseConditions>
        </oos:position>
      </oos:positions>
      <oos:finalPositions>
        <oos:purchase83/>
        <oos:purchase93/>
        <oos:outcomeIndicators>
          <oos:sumPushaseSingleSupplier4>99000</oos:sumPushaseSingleSupplier4>
          <oos:sumPushaseSingleSupplier5>997000</oos:sumPushaseSingleSupplier5>
          <oos:sumPushaseSmallBusiness>0</oos:sumPushaseSmallBusiness>
          <oos:sumPushaseRequest>0</oos:sumPushaseRequest>
          <oos:sumContractMaxPrice>2024600</oos:sumContractMaxPrice>
          <oos:sumPaymentsTotal>2024600</oos:sumPaymentsTotal>
        </oos:outcomeIndicators>
      </oos:finalPositions>
    </oos:providedPurchases>
    <oos:printForm>
      <oos:url>http://zakupki.gov.ru/pgz/printForm?type=PLAN_GRAPHIC&amp;id=446284</oos:url>
    </oos:printForm>
  </tenderPlan>
</export>
