<?xml version="1.0" encoding="UTF-8"?><export xmlns:xsi="http://www.w3.org/2001/XMLSchema-instance" xmlns="http://zakupki.gov.ru/oos/export/1" xmlns:oos="http://zakupki.gov.ru/oos/types/1">
  <tenderPlan schemeVersion="1.0">
    <oos:commonInfo>
      <oos:id>483615</oos:id>
      <oos:planNumber>44201403763000122</oos:planNumber>
      <oos:year>2014</oos:year>
      <oos:versionNumber>2</oos:versionNumber>
      <oos:owner>
        <oos:regNum>03763000122</oos:regNum>
        <oos:fullName>Муниципальное казенное образовательное учреждение &quot;Специальная (коррекционная) общеобразовательная школа VIII вида&quot;</oos:fullName>
      </oos:owner>
      <oos:createDate>2014-02-24T14:48:10Z</oos:createDate>
      <oos:description>План-график размещения заказов на поставку товаров, выполнение работ, оказание услуг для обеспечения государственных и муниципальных нужд на 2014 год</oos:description>
      <oos:confirmDate>2014-02-20T00:00:00Z</oos:confirmDate>
      <oos:publishDate>2014-02-24T15:25:03Z</oos:publishDate>
    </oos:commonInfo>
    <oos:customerInfo>
      <oos:customer>
        <oos:regNum>03763000122</oos:regNum>
        <oos:fullName>Муниципальное казенное образовательное учреждение &quot;Специальная (коррекционная) общеобразовательная школа VIII вида&quot;</oos:fullName>
      </oos:customer>
      <oos:OKTMO>
        <oos:code>79701000</oos:code>
        <oos:name>город Майкоп</oos:name>
      </oos:OKTMO>
    </oos:customerInfo>
    <oos:responsibleContactInfo>
      <oos:lastName>Василега</oos:lastName>
      <oos:firstName>Татьяна</oos:firstName>
      <oos:middleName>Геннадьевна</oos:middleName>
      <oos:phone>8-928-46-833-16</oos:phone>
      <oos:email>t.vasilega@gmail.com</oos:email>
    </oos:responsibleContactInfo>
    <oos:providedPurchases>
      <oos:positions>
        <oos:position>
          <oos:commonInfo>
            <oos:positionNumber>П44201403763000122000002</oos:positionNumber>
            <oos:amountKBKs>
              <oos:KBK>
                <oos:code>00000000000000000225</oos:code>
                <oos:amount>32000</oos:amount>
              </oos:KBK>
            </oos:amountKBKs>
            <oos:OKVEDs>
              <oos:OKVED>
                <oos:code>45.44.1</oos:code>
                <oos:name>Производство стекольных работ</oos:name>
              </oos:OKVED>
            </oos:OKVEDs>
            <oos:contractSubjectName>Замена оконных блоков в учебном помещении.</oos:contractSubjectName>
            <oos:contractMaxPrice>32000</oos:contractMaxPrice>
            <oos:payments>32000</oos:payments>
            <oos:contractCurrency>
              <oos:code>RUB</oos:code>
              <oos:name>Российский рубль</oos:name>
            </oos:contractCurrency>
            <oos:placingWay>
              <oos:code>ZK44</oos:code>
              <oos:name>Запрос котировок</oos:name>
            </oos:placingWay>
            <oos:positionModification>
              <oos:changeReason>
                <oos:id>5</oos:id>
                <oos:name>Возникновение непредвиденных обстоятельств</oos:name>
              </oos:changeReason>
              <oos:additionalInfo>Приказ № 40 от 20.02.2014г. &quot;О внесении изменений в «План-график на поставки товаров,
выполнение работ, оказание услуг для нужд МКОУ «СКОШ VIII вида»&quot;.</oos:additionalInfo>
            </oos:positionModification>
            <oos:positionPublishDate>2014-02-24T15:25:03Z</oos:positionPublishDate>
            <oos:noPublicDiscussion>false</oos:noPublicDiscussion>
          </oos:commonInfo>
          <oos:products>
            <oos:product>
              <oos:OKPD>
                <oos:code/>
              </oos:OKPD>
              <oos:name>Замена оконных блоков в учебном помещении.</oos:name>
              <oos:internationalName>-</oos:internationalName>
              <oos:minRequirement>1)работа должна выполняться с соблюдением технологических процессов;
2)материалы, приобретаемые для выполнения работ должны быть высокого качества и иметь санитарно-гигиенические сертификаты;
3) наличие необходимых инструментов и оборудования для выполнения работ;
4) исправление замечаний и обнаруженных дефектов в максимально короткие сроки;
5) гарантия выполненных работ – 1 год;
6) предоставление исполнительной документации на выполненные работы.
</oos:minRequirement>
              <oos:OKEI>
                <oos:code>796</oos:code>
                <oos:name>Штука</oos:name>
              </oos:OKEI>
              <oos:sumMax>32000</oos:sumMax>
              <oos:price>0</oos:price>
              <oos:quantityUndefined>false</oos:quantityUndefined>
              <oos:quantity>3</oos:quantity>
              <oos:quantityCurrentYear>3</oos:quantityCurrentYear>
            </oos:product>
          </oos:products>
          <oos:purchaseConditions>
            <oos:advance>-</oos:advance>
            <oos:purchaseGraph>
              <oos:purchasePlacingTerm>
                <oos:month>6</oos:month>
                <oos:year>2014</oos:year>
              </oos:purchasePlacingTerm>
              <oos:contractExecutionTerm>
                <oos:month>7</oos:month>
                <oos:year>2014</oos:year>
              </oos:contractExecutionTerm>
              <oos:contractExecutionStages>-</oos:contractExecutionStages>
              <oos:periodicity>В течении срока действия договора.</oos:periodicity>
            </oos:purchaseGraph>
            <oos:preferensesRequirement>
              <oos:requirements>
                <oos:requirement>
                  <oos:code>8361040</oos:code>
                  <oos:name>Единые требования к участникам (в соответствии  с частью 1 Статьи 31 Федерального закона № 44-ФЗ)</oos:name>
                </oos:requirement>
                <oos:requirement>
                  <oos:code>8361977</oos:code>
                  <oos:name>Требование о наличии необходимого количества специалистов и иных работников определенного уровня квалификации для исполнения контракта (в соответствии  с пунктом 4 части 2 Статьи 31 Федерального закона № 44-ФЗ)</oos:name>
                </oos:requirement>
                <oos:requirement>
                  <oos:code>8403975</oos:code>
                  <oos:name>Требование об отсутствии в предусмотренном настоящим Федеральным законом реестре недобросовестных поставщиков (подрядчиков, исполнителей) информации об участнике закупки, в том числе информации об учредителях, о членах коллегиального исполнительного органа, лице, исполняющем функции единоличного исполнительного органа участника закупки - юридического лица (в соответствии с частью 1.1 Статьи 31 Федерального закона № 44-ФЗ)</oos:name>
                </oos:requirement>
                <oos:requirement>
                  <oos:code>8361976</oos:code>
                  <oos:name>Требование о наличии опыта работы, связанного с предметом контракта, и деловой репутации (в соответствии  с пунктом 3 части 2 Статьи 31 Федерального закона № 44-ФЗ)</oos:name>
                </oos:requirement>
                <oos:requirement>
                  <oos:code>8361039</oos:code>
                  <oos:name>Требование о выполнении участниками запроса котировок за последние три года, предшествующие дате размещения извещения о проведении запроса котировок, работ по строительству, реконструкции, капитальному ремонту объектов капитального строительства (в соответствии с Частью 16 Статьи 112 Федерального закона № 44-ФЗ)</oos:name>
                </oos:requirement>
                <oos:requirement>
                  <oos:code>8361974</oos:code>
                  <oos:name>Требование о наличии финансовых ресурсов для исполнения контракта (в соответствии  с пунктом 1 части 2 Статьи 31 Федерального закона № 44-ФЗ)</oos:name>
                </oos:requirement>
              </oos:requirements>
            </oos:preferensesRequirement>
          </oos:purchaseConditions>
        </oos:position>
        <oos:position>
          <oos:commonInfo>
            <oos:positionNumber>П44201403763000122000001</oos:positionNumber>
            <oos:amountKBKs>
              <oos:KBK>
                <oos:code>00000000000000000225</oos:code>
                <oos:amount>115203.73</oos:amount>
              </oos:KBK>
            </oos:amountKBKs>
            <oos:OKVEDs>
              <oos:OKVED>
                <oos:code>45.44.2</oos:code>
                <oos:name>Производство малярных работ</oos:name>
              </oos:OKVED>
            </oos:OKVEDs>
            <oos:contractSubjectName>Текущий ремонт учебного кабинета для субъектов малого предпринимательства</oos:contractSubjectName>
            <oos:contractMaxPrice>115203.73</oos:contractMaxPrice>
            <oos:payments>115203.73</oos:payments>
            <oos:contractCurrency>
              <oos:code>RUB</oos:code>
              <oos:name>Российский рубль</oos:name>
            </oos:contractCurrency>
            <oos:placingWay>
              <oos:code>EA44</oos:code>
              <oos:name>Электронный аукцион</oos:name>
            </oos:placingWay>
            <oos:positionModification>
              <oos:changeReason>
                <oos:id>5</oos:id>
                <oos:name>Возникновение непредвиденных обстоятельств</oos:name>
              </oos:changeReason>
              <oos:additionalInfo>Приказ № 40 от 20.02.2014г. &quot;О внесении изменений в «План-график на поставки товаров,
выполнение работ, оказание услуг для нужд МКОУ «СКОШ VIII вида»&quot;.</oos:additionalInfo>
            </oos:positionModification>
            <oos:positionPublishDate>2014-02-24T15:25:03Z</oos:positionPublishDate>
            <oos:noPublicDiscussion>false</oos:noPublicDiscussion>
          </oos:commonInfo>
          <oos:products>
            <oos:product>
              <oos:OKPD>
                <oos:code/>
              </oos:OKPD>
              <oos:name>Текущий ремонт учебного кабинета для субъектов малого предпринимательства</oos:name>
              <oos:internationalName>-</oos:internationalName>
              <oos:minRequirement>1) работа должна выполняться с соблюдением технологических процессов;
2) материалы, приобретаемые для выполнения работ должны быть высокого качества и иметь санитарно-гигиенические сертификаты;
3) вид и цветовое решение отделочных строительных материалов должны быть согласованы с заказчиком;
4) наличие необходимых инструментов и оборудования для выполнения работ;
5 )исправление замечаний и обнаруженных дефектов в максимально короткие сроки;
6) гарантия выполненных работ – 1 год;
7) предоставление исполнительной документации на выполненные работы.

</oos:minRequirement>
              <oos:OKEI>
                <oos:code/>
              </oos:OKEI>
              <oos:sumMax>115203.73</oos:sumMax>
              <oos:price>0</oos:price>
              <oos:quantityUndefined>true</oos:quantityUndefined>
            </oos:product>
          </oos:products>
          <oos:purchaseConditions>
            <oos:advance>-</oos:advance>
            <oos:purchaseGraph>
              <oos:purchasePlacingTerm>
                <oos:month>6</oos:month>
                <oos:year>2014</oos:year>
              </oos:purchasePlacingTerm>
              <oos:contractExecutionTerm>
                <oos:month>8</oos:month>
                <oos:year>2014</oos:year>
              </oos:contractExecutionTerm>
              <oos:contractExecutionStages>-</oos:contractExecutionStages>
              <oos:periodicity>В течении периода выполнения работ.</oos:periodicity>
            </oos:purchaseGraph>
            <oos:preferensesRequirement>
              <oos:preferenses>
                <oos:preferense>
                  <oos:code>8361034</oos:code>
                  <oos:name>Субъектам малого предпринимательства (в соответствии со Статьей 30 Федерального закона № 44-ФЗ)</oos:name>
                </oos:preferense>
              </oos:preferenses>
              <oos:requirements>
                <oos:requirement>
                  <oos:code>8361975</oos:code>
                  <oos:name>Требование о наличии на праве собственности или ином законном основании оборудования и других материальных ресурсов для исполнения контракта (в соответствии  с пунктом 2 части 2 Статьи 31 Федерального закона № 44-ФЗ)</oos:name>
                </oos:requirement>
                <oos:requirement>
                  <oos:code>8361974</oos:code>
                  <oos:name>Требование о наличии финансовых ресурсов для исполнения контракта (в соответствии  с пунктом 1 части 2 Статьи 31 Федерального закона № 44-ФЗ)</oos:name>
                </oos:requirement>
                <oos:requirement>
                  <oos:code>8361977</oos:code>
                  <oos:name>Требование о наличии необходимого количества специалистов и иных работников определенного уровня квалификации для исполнения контракта (в соответствии  с пунктом 4 части 2 Статьи 31 Федерального закона № 44-ФЗ)</oos:name>
                </oos:requirement>
                <oos:requirement>
                  <oos:code>8361040</oos:code>
                  <oos:name>Единые требования к участникам (в соответствии  с частью 1 Статьи 31 Федерального закона № 44-ФЗ)</oos:name>
                </oos:requirement>
                <oos:requirement>
                  <oos:code>8361976</oos:code>
                  <oos:name>Требование о наличии опыта работы, связанного с предметом контракта, и деловой репутации (в соответствии  с пунктом 3 части 2 Статьи 31 Федерального закона № 44-ФЗ)</oos:name>
                </oos:requirement>
              </oos:requirements>
            </oos:preferensesRequirement>
          </oos:purchaseConditions>
        </oos:position>
        <oos:position>
          <oos:commonInfo>
            <oos:positionNumber>П44201403763000122000003</oos:positionNumber>
            <oos:amountKBKs>
              <oos:KBK>
                <oos:code>00000000000000000226</oos:code>
                <oos:amount>34000</oos:amount>
              </oos:KBK>
            </oos:amountKBKs>
            <oos:OKVEDs>
              <oos:OKVED>
                <oos:code>74.30.8</oos:code>
                <oos:name>Сертификация продукции и услуг</oos:name>
              </oos:OKVED>
            </oos:OKVEDs>
            <oos:contractSubjectName>Аттестация рабочих мест по охране труда</oos:contractSubjectName>
            <oos:contractMaxPrice>34000</oos:contractMaxPrice>
            <oos:payments>34000</oos:payments>
            <oos:contractCurrency>
              <oos:code>RUB</oos:code>
              <oos:name>Российский рубль</oos:name>
            </oos:contractCurrency>
            <oos:placingWay>
              <oos:code>ZP44</oos:code>
              <oos:name>Запрос предложений</oos:name>
            </oos:placingWay>
            <oos:positionModification>
              <oos:changeReason>
                <oos:id>5</oos:id>
                <oos:name>Возникновение непредвиденных обстоятельств</oos:name>
              </oos:changeReason>
              <oos:additionalInfo>Приказ № 40 от 20.02.2014г. &quot;О внесении изменений в «План-график на поставки товаров,
выполнение работ, оказание услуг для нужд МКОУ «СКОШ VIII вида»&quot;.

</oos:additionalInfo>
            </oos:positionModification>
            <oos:positionPublishDate>2014-02-24T15:25:03Z</oos:positionPublishDate>
            <oos:noPublicDiscussion>false</oos:noPublicDiscussion>
          </oos:commonInfo>
          <oos:products>
            <oos:product>
              <oos:OKPD>
                <oos:code/>
              </oos:OKPD>
              <oos:name>Аттестация рабочих мест по охране труда</oos:name>
              <oos:internationalName>-</oos:internationalName>
              <oos:minRequirement>1. Услуги по аттестации рабочих мест по условиям труда должны быть проведены в соответствии со статьей 212 Трудового Кодекса РФ и в соответствии с «Порядком проведения аттестации рабочих мест по условиям труда» утв. Приказом Министерства здравоохранения и социального развития Российской Федерации от 26 апреля 2011 г. N 342н
2. По результатам оказания услуг Исполнитель предоставляет документацию предусмотренную Порядком проведения аттестации.
3. Произвести измерение параметров вредных и опасных производственных факторов, определить параметры тяжести и напряженности на каждом рабочем месте, дать оценку травмобезопасности рабочих мест и обеспеченности СИЗ, с оформлением соответствующих протоколов, ведомостей, экспертного заключения об аттестации рабочих мест по условиям труда в соответствии с требованиями Порядка проведения аттестации.
</oos:minRequirement>
              <oos:OKEI>
                <oos:code/>
              </oos:OKEI>
              <oos:sumMax>34000</oos:sumMax>
              <oos:price>0</oos:price>
              <oos:quantityUndefined>true</oos:quantityUndefined>
            </oos:product>
          </oos:products>
          <oos:purchaseConditions>
            <oos:advance>-</oos:advance>
            <oos:purchaseGraph>
              <oos:purchasePlacingTerm>
                <oos:month>8</oos:month>
                <oos:year>2014</oos:year>
              </oos:purchasePlacingTerm>
              <oos:contractExecutionTerm>
                <oos:month>11</oos:month>
                <oos:year>2014</oos:year>
              </oos:contractExecutionTerm>
              <oos:contractExecutionStages>-</oos:contractExecutionStages>
              <oos:periodicity>В период действия договора.</oos:periodicity>
            </oos:purchaseGraph>
            <oos:preferensesRequirement>
              <oos:requirements>
                <oos:requirement>
                  <oos:code>8361040</oos:code>
                  <oos:name>Единые требования к участникам (в соответствии  с частью 1 Статьи 31 Федерального закона № 44-ФЗ)</oos:name>
                </oos:requirement>
                <oos:requirement>
                  <oos:code>8361977</oos:code>
                  <oos:name>Требование о наличии необходимого количества специалистов и иных работников определенного уровня квалификации для исполнения контракта (в соответствии  с пунктом 4 части 2 Статьи 31 Федерального закона № 44-ФЗ)</oos:name>
                </oos:requirement>
                <oos:requirement>
                  <oos:code>8403975</oos:code>
                  <oos:name>Требование об отсутствии в предусмотренном настоящим Федеральным законом реестре недобросовестных поставщиков (подрядчиков, исполнителей) информации об участнике закупки, в том числе информации об учредителях, о членах коллегиального исполнительного органа, лице, исполняющем функции единоличного исполнительного органа участника закупки - юридического лица (в соответствии с частью 1.1 Статьи 31 Федерального закона № 44-ФЗ)</oos:name>
                </oos:requirement>
                <oos:requirement>
                  <oos:code>8361976</oos:code>
                  <oos:name>Требование о наличии опыта работы, связанного с предметом контракта, и деловой репутации (в соответствии  с пунктом 3 части 2 Статьи 31 Федерального закона № 44-ФЗ)</oos:name>
                </oos:requirement>
                <oos:requirement>
                  <oos:code>8361975</oos:code>
                  <oos:name>Требование о наличии на праве собственности или ином законном основании оборудования и других материальных ресурсов для исполнения контракта (в соответствии  с пунктом 2 части 2 Статьи 31 Федерального закона № 44-ФЗ)</oos:name>
                </oos:requirement>
              </oos:requirements>
            </oos:preferensesRequirement>
          </oos:purchaseConditions>
        </oos:position>
      </oos:positions>
      <oos:finalPositions>
        <oos:purchase83>
          <oos:teachingService>
            <oos:finances>
              <oos:amountKBKs>
                <oos:KBK>
                  <oos:code>00000000000000000226</oos:code>
                  <oos:amount>34000</oos:amount>
                </oos:KBK>
                <oos:KBK>
                  <oos:code>00000000000000000225</oos:code>
                  <oos:amount>115203.73</oos:amount>
                </oos:KBK>
                <oos:KBK>
                  <oos:code>00000000000000000225</oos:code>
                  <oos:amount>32000</oos:amount>
                </oos:KBK>
              </oos:amountKBKs>
            </oos:finances>
          </oos:teachingService>
          <oos:guideService>
            <oos:finances>
              <oos:amountKBKs>
                <oos:KBK>
                  <oos:code>00000000000000000226</oos:code>
                  <oos:amount>34000</oos:amount>
                </oos:KBK>
                <oos:KBK>
                  <oos:code>00000000000000000225</oos:code>
                  <oos:amount>115203.73</oos:amount>
                </oos:KBK>
                <oos:KBK>
                  <oos:code>00000000000000000225</oos:code>
                  <oos:amount>32000</oos:amount>
                </oos:KBK>
              </oos:amountKBKs>
            </oos:finances>
          </oos:guideService>
          <oos:medicine>
            <oos:finances>
              <oos:amountKBKs>
                <oos:KBK>
                  <oos:code>00000000000000000226</oos:code>
                  <oos:amount>34000</oos:amount>
                </oos:KBK>
                <oos:KBK>
                  <oos:code>00000000000000000225</oos:code>
                  <oos:amount>115203.73</oos:amount>
                </oos:KBK>
                <oos:KBK>
                  <oos:code>00000000000000000225</oos:code>
                  <oos:amount>32000</oos:amount>
                </oos:KBK>
              </oos:amountKBKs>
            </oos:finances>
          </oos:medicine>
        </oos:purchase83>
        <oos:purchase93>
          <oos:purchaseAmountLess100>
            <oos:finances>
              <oos:amountKBKs>
                <oos:KBK>
                  <oos:code>00000000000000000226</oos:code>
                  <oos:amount>34000</oos:amount>
                </oos:KBK>
                <oos:KBK>
                  <oos:code>00000000000000000225</oos:code>
                  <oos:amount>115203.73</oos:amount>
                </oos:KBK>
                <oos:KBK>
                  <oos:code>00000000000000000225</oos:code>
                  <oos:amount>32000</oos:amount>
                </oos:KBK>
              </oos:amountKBKs>
            </oos:finances>
          </oos:purchaseAmountLess100>
          <oos:purchaseAmountLess400>
            <oos:finances>
              <oos:amountKBKs>
                <oos:KBK>
                  <oos:code>00000000000000000226</oos:code>
                  <oos:amount>34000</oos:amount>
                </oos:KBK>
                <oos:KBK>
                  <oos:code>00000000000000000225</oos:code>
                  <oos:amount>115203.73</oos:amount>
                </oos:KBK>
                <oos:KBK>
                  <oos:code>00000000000000000225</oos:code>
                  <oos:amount>32000</oos:amount>
                </oos:KBK>
              </oos:amountKBKs>
            </oos:finances>
          </oos:purchaseAmountLess400>
        </oos:purchase93>
        <oos:outcomeIndicators>
          <oos:sumPushaseSingleSupplier4>0</oos:sumPushaseSingleSupplier4>
          <oos:sumPushaseSingleSupplier5>181203.72</oos:sumPushaseSingleSupplier5>
          <oos:sumPushaseSmallBusiness>115203.73</oos:sumPushaseSmallBusiness>
          <oos:sumPushaseRequest>32000</oos:sumPushaseRequest>
          <oos:sumContractMaxPrice>181203.73</oos:sumContractMaxPrice>
          <oos:sumPaymentsTotal>181203.73</oos:sumPaymentsTotal>
        </oos:outcomeIndicators>
      </oos:finalPositions>
    </oos:providedPurchases>
    <oos:printForm>
      <oos:url>http://zakupki.gov.ru/pgz/printForm?type=PLAN_GRAPHIC&amp;id=483615</oos:url>
    </oos:printForm>
  </tenderPlan>
</export>
